zalabim/DejaVuSansMono.ttf
zalabim/calibri.ttf
zalabim/mplus-1m-regular.ttf
zalabim/zalabim.py
zalabim-24.1.11.dist-info/METADATA
zalabim-24.1.11.dist-info/WHEEL
zalabim-24.1.11.dist-info/top_level.txt
zalabim-24.1.11.dist-info/RECORD
