Metadata-Version: 2.1
Name: zalabim
Version: 24.1.11
Summary: salabim - discrete event simulation in Python
Author-email: Ruud van der Ham <rt.van.der.ham@gmail.com>
Project-URL: Homepage, https://github.com/salabim/zalabim
Project-URL: Repository, https://github.com/salabim/zalabim
Classifier: Development Status :: 5 - Production/Stable
Classifier: License :: OSI Approved :: MIT License
Classifier: Programming Language :: Python :: 3 :: Only
Requires-Python: >=3.7
